test.py
gw_sys_core/__init__.py
gw_sys_core/gwis/Exceptions.py
gw_sys_core/gwis/__init__.py
gw_sys_core/gwis/ids.py
gw_sys_core-0.0.0.0.10.dist-info/LICENSE
gw_sys_core-0.0.0.0.10.dist-info/METADATA
gw_sys_core-0.0.0.0.10.dist-info/WHEEL
gw_sys_core-0.0.0.0.10.dist-info/top_level.txt
gw_sys_core-0.0.0.0.10.dist-info/RECORD
