Metadata-Version: 2.2
Name: gw-sys-core
Version: 0.0.0.0.10
Summary: gw-sys-core
Home-page: https://github.com/KeyisB/libs/tree/main/gw-sys-core
Author: KeyisB
Author-email: keyisb.pip@gmail.com
License: MMB License v1.0
Classifier: Programming Language :: Python :: 3
Classifier: Operating System :: OS Independent
Requires-Python: >=3.12
License-File: LICENSE
Dynamic: author
Dynamic: author-email
Dynamic: classifier
Dynamic: description
Dynamic: description-content-type
Dynamic: home-page
Dynamic: license
Dynamic: requires-python
Dynamic: summary
